ijson/__init__.py
ijson/benchmark.py
ijson/common.py
ijson/compat.py
ijson/dump.py
ijson/utils.py
ijson/utils35.py
ijson/version.py
ijson/backends/__init__.py
ijson/backends/_yajl2.cpython-310-i386-linux-gnu.so
ijson/backends/_yajl2_ctypes_common.py
ijson/backends/python.py
ijson/backends/yajl.py
ijson/backends/yajl2.py
ijson/backends/yajl2_c.py
ijson/backends/yajl2_cffi.py
ijson.libs/libyajl-f1f781fb.so.2.1.1
ijson-3.4.0.post0.dist-info/METADATA
ijson-3.4.0.post0.dist-info/WHEEL
ijson-3.4.0.post0.dist-info/top_level.txt
ijson-3.4.0.post0.dist-info/RECORD
ijson-3.4.0.post0.dist-info/licenses/LICENSE.txt
