Metadata-Version: 2.4
Name: ijson
Version: 3.4.0.post0
Summary: Iterative JSON parser with standard Python iterator interfaces
Author-email: Rodrigo Tobar <rtobar@icrar.org>, Ivan Sagalaev <maniac@softwaremaniacs.org>
License-Expression: BSD-3-Clause AND ISC
Project-URL: Homepage, https://github.com/ICRAR/ijson
Classifier: Development Status :: 5 - Production/Stable
Classifier: Programming Language :: Python :: 3.9
Classifier: Programming Language :: Python :: 3.10
Classifier: Programming Language :: Python :: 3.11
Classifier: Programming Language :: Python :: 3.12
Classifier: Programming Language :: Python :: 3.13
Classifier: Programming Language :: Python :: 3.14
Classifier: Programming Language :: Python :: Implementation :: CPython
Classifier: Programming Language :: Python :: Implementation :: PyPy
Classifier: Topic :: Software Development :: Libraries :: Python Modules
Requires-Python: >=3.9
License-File: LICENSE.txt
Dynamic: license-file
